flake8_typing_imports.py
flake8_typing_imports-1.17.0.dist-info/LICENSE
flake8_typing_imports-1.17.0.dist-info/METADATA
flake8_typing_imports-1.17.0.dist-info/WHEEL
flake8_typing_imports-1.17.0.dist-info/entry_points.txt
flake8_typing_imports-1.17.0.dist-info/top_level.txt
flake8_typing_imports-1.17.0.dist-info/RECORD
